text_classifier_sdk/__init__.py
text_classifier_sdk/classifier.py
text_classifier_sdk/model_utils.py
text_classifier_sdk/train.py
text_classifier_sdk-0.1.6.dist-info/LICENSE
text_classifier_sdk-0.1.6.dist-info/METADATA
text_classifier_sdk-0.1.6.dist-info/WHEEL
text_classifier_sdk-0.1.6.dist-info/top_level.txt
text_classifier_sdk-0.1.6.dist-info/RECORD
