Metadata-Version: 2.2
Name: text_classifier_sdk
Version: 0.1.6
Summary: A simple text classification SDK.
Home-page: https://github.com/iyke0z/text-classifier-sdk
Author: Ikenna Anikwe
Author-email: ikennaedmundanikwe@gmail.com
License: MIT
Requires-Python: >=3.11
License-File: LICENSE
Requires-Dist: torch
Requires-Dist: transformers
Requires-Dist: pandas
Requires-Dist: scikit-learn
Requires-Dist: requests
Dynamic: author
Dynamic: author-email
Dynamic: description
Dynamic: description-content-type
Dynamic: home-page
Dynamic: license
Dynamic: requires-dist
Dynamic: requires-python
Dynamic: summary
